eesr/__init__.py
eesr/__main__.py
eesr/interface.py
eesr/util.py
eesr/analysis/__init__.py
eesr/analysis/entsoe_caching.py
eesr/analysis/grid.py
eesr/analysis/opendc_preprocess.py
eesr/analysis/util.py
eesr/analysis/cache/__init__.py
eesr/analysis/data/LCA_CO2_BEST.csv
eesr/analysis/data/LCA_CO2_WORST.csv
eesr/reporting/__init__.py
eesr/reporting/create_rating.py
eesr/reporting/grapher.py
eesr/reporting/html_builder.py
eesr/reporting/validator.py
eesr/reporting/library/metrics_library.json
eesr/reporting/library/profiles/ee_prof.json
eesr/reporting/library/profiles/std_prof.json
eesr/reporting/library/profiles/sus_prof.json
eesr/reporting/library/schemas/metrics_input_schema.json
eesr/reporting/library/schemas/profile_schema.json
eesr/reporting/library/templates/compact_template.html
eesr/reporting/library/templates/std_template.html
eesr/reporting/library/templates/content/energy_sources.svg
eesr/reporting/library/templates/content/metric_compare.svg
eesr/reporting/library/templates/content/opendc_logo.png
eesr/reporting/library/templates/content/opendc_logo.svg
eesr/reporting/library/templates/content/rating_ap.svg
eesr/reporting/library/templates/content/rn_energy_adapt.svg
eesr/reporting/library/templates/content/rn_energy_adapt1.svg
eesr/test/test_values.json
opendc-eesr/__init__.py
opendc-eesr/__main__.py
opendc-eesr/interface.py
opendc-eesr/util.py
opendc_eesr-0.0.5.dist-info/LICENSE
opendc_eesr-0.0.5.dist-info/METADATA
opendc_eesr-0.0.5.dist-info/WHEEL
opendc_eesr-0.0.5.dist-info/top_level.txt
opendc_eesr-0.0.5.dist-info/RECORD
